sns_sub_manager/__init__.py
sns_sub_manager/config.py
sns_sub_manager/main.py
sns_sub_manager/py.typed
sns_sub_manager/routes/__init__.py
sns_sub_manager/routes/list.py
sns_sub_manager/routes/subscribe.py
sns_sub_manager/schemas/__init__.py
sns_sub_manager/schemas/subscribe.py
sns_sub_manager/utils/__init__.py
sns_sub_manager/utils/aws.py
sns_sub_manager/utils/logging.py
sns_sub_manager-0.0.2.dist-info/entry_points.txt
sns_sub_manager-0.0.2.dist-info/LICENSE
sns_sub_manager-0.0.2.dist-info/WHEEL
sns_sub_manager-0.0.2.dist-info/METADATA
sns_sub_manager-0.0.2.dist-info/RECORD
