Metadata-Version: 2.1
Name: sns-sub-manager
Version: 0.0.2
Summary: AWS SNS Subscription Manager
Home-page: https://github.com/andrewthetechie/sns-sub-manager
License: MIT
Author: Andrew Herrington
Author-email: andrew.the.techie@gmail.com
Requires-Python: >=3.9,<4.0
Classifier: Development Status :: 3 - Alpha
Classifier: License :: OSI Approved :: MIT License
Classifier: Programming Language :: Python :: 3
Classifier: Programming Language :: Python :: 3.10
Classifier: Programming Language :: Python :: 3.9
Requires-Dist: aiobotocore (>=2.2.0,<3.0.0)
Requires-Dist: email-validator (>=1.2.0,<2.0.0)
Requires-Dist: fastapi (>=0.75.2,<0.76.0)
Requires-Dist: fastapi-health (>=0.4.0,<0.5.0)
Requires-Dist: phonenumbers (>=8.12.47,<9.0.0)
Requires-Dist: uvicorn (>=0.17.6,<0.18.0)
Project-URL: Changelog, https://github.com/andrewthetechie/sns-sub-manager/releases
Project-URL: Documentation, https://sns-sub-manager.readthedocs.io
Project-URL: Repository, https://github.com/andrewthetechie/sns-sub-manager
